sandal/__init__.py
sandal/autoroot.py
sandal/cli.py
sandal/loghelper.py
sandal/notebook.py
sandal/project.py
sandal/root.py
sandal-0.1.0.dist-info/LICENSE.md
sandal-0.1.0.dist-info/METADATA
sandal-0.1.0.dist-info/WHEEL
sandal-0.1.0.dist-info/top_level.txt
sandal-0.1.0.dist-info/RECORD
